soft_spot/__init__.py
soft_spot/__main__.py
soft_spot/configuration.py
soft_spot/fab.py
soft_spot/implementations/__init__.py
soft_spot/implementations/price.py
soft_spot/implementations/request.py
soft_spot/implementations/scripts.py
soft_spot/implementations/volumes.py
soft_spot-0.4.0.dist-info/entry_points.txt
soft_spot-0.4.0.dist-info/WHEEL
soft_spot-0.4.0.dist-info/METADATA
soft_spot-0.4.0.dist-info/RECORD
