Metadata-Version: 2.1
Name: soft-spot
Version: 0.4.0
Summary: Move to a land of Spot AWS instances
Home-page: https://github.com/fferegrino/soft-spot
License: MIT
Author: Antonio Feregrino
Author-email: antonio.feregrino@gmail.com
Requires-Python: >=3.6,<4.0
Classifier: Development Status :: 3 - Alpha
Classifier: License :: OSI Approved :: MIT License
Classifier: Programming Language :: Python :: 3
Classifier: Programming Language :: Python :: 3.6
Classifier: Programming Language :: Python :: 3.7
Classifier: Topic :: Utilities
Requires-Dist: backoff (>=1.8,<2.0)
Requires-Dist: boto3 (>=1.9,<2.0)
Requires-Dist: click (>=7.0,<8.0)
Requires-Dist: fabric (>=2.5,<3.0)
Requires-Dist: tabulate (>=0.8.5,<0.9.0)
Project-URL: Repository, https://github.com/fferegrino/soft-spot
